alembic/env.py
cli/__init__.py
cli/app.py
cli/bash_cli.py
cli/db_cli.py
cli/db_manage_cli.py
cli/item_cli.py
cli/item_detail_cli.py
crud/__init__.py
crud/item_crud.py
crud/item_detail_crud.py
dao/__init__.py
dao/item_dao.py
dao/item_detail_dao.py
dashboard/__init__.py
database/__init__.py
database/models.py
etl/__init__.py
shared/__init__.py
shared/db_check.py
shared/db_path_config.py
sqlitekit-3.dist-info/METADATA
sqlitekit-3.dist-info/WHEEL
sqlitekit-3.dist-info/entry_points.txt
sqlitekit-3.dist-info/top_level.txt
sqlitekit-3.dist-info/RECORD
