Metadata-Version: 2.4
Name: sqlitekit
Version: 3
Summary: cli tool for a sqlite database of items and item details (scaffold layer 1)
Author: Silcrow
Requires-Dist: click
Requires-Dist: alembic
Requires-Dist: pendulum
Requires-Dist: sqlalchemy
